svaponi/__init__.py
svaponi-0.0.1.dist-info/METADATA
svaponi-0.0.1.dist-info/WHEEL
svaponi-0.0.1.dist-info/top_level.txt
svaponi-0.0.1.dist-info/RECORD
